{
  "nav_history": [
    {
      "date": "2026-03-14",
      "nav": 668.86,
      "ticker": "PSQ",
      "state": "A",
      "cash": 290.62,
      "remaining_cash": 8.09
    },
    {
      "date": "2026-03-17",
      "nav": 662.87,
      "ticker": "PSQ",
      "state": "A",
      "cash": 8.09,
      "remaining_cash": 8.09
    },
    {
      "date": "2026-03-18",
      "nav": 659.09,
      "ticker": "PSQ",
      "state": "A",
      "cash": 8.09,
      "remaining_cash": 8.09
    },
    {
      "date": "2026-03-19",
      "nav": 1674.06,
      "ticker": "PSQ",
      "state": "A",
      "cash": 1014.85,
      "remaining_cash": 41.76
    },
    {
      "date": "2026-03-20",
      "nav": 2079.42,
      "ticker": "PSQ",
      "state": "A",
      "cash": 439.34,
      "remaining_cash": 29.32
    },
    {
      "date": "2026-03-21",
      "nav": 2960.92,
      "ticker": "PSQ",
      "state": "A",
      "cash": 864.02,
      "remaining_cash": 57.77
    },
    {
      "date": "2026-03-24",
      "nav": 4234.86,
      "ticker": "PSQ",
      "state": "A",
      "cash": 1376.46,
      "remaining_cash": 74.3
    },
    {
      "date": "2026-03-25",
      "nav": 4264.09,
      "ticker": "PSQ",
      "state": "A",
      "cash": 72.09,
      "remaining_cash": 8.09
    },
    {
      "date": "2026-03-26",
      "nav": 4218.59,
      "ticker": "PSQ",
      "state": "A",
      "cash": 8.48,
      "remaining_cash": 8.48
    },
    {
      "date": "2026-03-27",
      "nav": 4313.02,
      "ticker": "PSQ",
      "state": "A",
      "cash": 8.48,
      "remaining_cash": 8.48
    },
    {
      "date": "2026-03-28",
      "nav": 5728.86,
      "ticker": "PSQ",
      "state": "A",
      "cash": 1329.22,
      "remaining_cash": 72.18
    },
    {
      "date": "2026-03-31",
      "nav": 5772.7,
      "ticker": "PSQ",
      "state": "A",
      "cash": 69.85,
      "remaining_cash": 3.16
    },
    {
      "date": "2026-04-01",
      "nav": 5560.68,
      "ticker": "TQQQ",
      "state": "B",
      "cash": 3.05,
      "remaining_cash": 238.11
    },
    {
      "date": "2026-04-02",
      "nav": 20.41,
      "ticker": "TQQQ",
      "state": "B",
      "cash": 20.41,
      "remaining_cash": 20.41
    },
    {
      "date": "2026-04-03",
      "nav": 6638.47,
      "ticker": "SGOV",
      "state": "D",
      "cash": 225.63,
      "remaining_cash": 330.49
    }
  ],
  "trade_log": [
    {
      "date": "2026-03-14",
      "action": "hold",
      "from_ticker": "PSQ",
      "to_ticker": "PSQ",
      "state": "A",
      "nav": 668.86,
      "strategy_return_pct": 0.0
    },
    {
      "date": "2026-03-17",
      "action": "hold",
      "from_ticker": "PSQ",
      "to_ticker": "PSQ",
      "state": "A",
      "nav": 662.87,
      "strategy_return_pct": -0.9
    },
    {
      "date": "2026-03-18",
      "action": "hold",
      "from_ticker": "PSQ",
      "to_ticker": "PSQ",
      "state": "A",
      "nav": 659.09,
      "strategy_return_pct": -1.46
    },
    {
      "date": "2026-03-19",
      "action": "add",
      "from_ticker": "PSQ",
      "to_ticker": "PSQ",
      "state": "A",
      "nav": 1674.06,
      "strategy_return_pct": -0.09
    },
    {
      "date": "2026-03-20",
      "action": "add",
      "from_ticker": "PSQ",
      "to_ticker": "PSQ",
      "state": "A",
      "nav": 2079.42,
      "strategy_return_pct": 0.3
    },
    {
      "date": "2026-03-21",
      "action": "add",
      "from_ticker": "PSQ",
      "to_ticker": "PSQ",
      "state": "A",
      "nav": 2960.92,
      "strategy_return_pct": 1.82
    },
    {
      "date": "2026-03-24",
      "action": "add",
      "from_ticker": "PSQ",
      "to_ticker": "PSQ",
      "state": "A",
      "nav": 4234.86,
      "strategy_return_pct": 0.2
    },
    {
      "date": "2026-03-25",
      "action": "add",
      "from_ticker": "PSQ",
      "to_ticker": "PSQ",
      "state": "A",
      "nav": 4264.09,
      "strategy_return_pct": 0.89
    },
    {
      "date": "2026-03-26",
      "action": "hold",
      "from_ticker": "PSQ",
      "to_ticker": "PSQ",
      "state": "A",
      "nav": 4218.59,
      "strategy_return_pct": -0.19
    },
    {
      "date": "2026-03-27",
      "action": "hold",
      "from_ticker": "PSQ",
      "to_ticker": "PSQ",
      "state": "A",
      "nav": 4313.02,
      "strategy_return_pct": 2.04
    },
    {
      "date": "2026-03-28",
      "action": "add",
      "from_ticker": "PSQ",
      "to_ticker": "PSQ",
      "state": "A",
      "nav": 5728.86,
      "strategy_return_pct": 3.27
    },
    {
      "date": "2026-03-31",
      "action": "add",
      "from_ticker": "PSQ",
      "to_ticker": "PSQ",
      "state": "A",
      "nav": 5772.7,
      "strategy_return_pct": 4.06
    },
    {
      "date": "2026-04-01",
      "action": "buy",
      "from_ticker": "PSQ",
      "to_ticker": "TQQQ",
      "state": "B",
      "nav": 5560.68,
      "strategy_return_pct": 0.24
    },
    {
      "date": "2026-04-02",
      "action": "hold",
      "from_ticker": "-",
      "to_ticker": "TQQQ",
      "state": "B",
      "nav": 20.41,
      "strategy_return_pct": -99.63
    },
    {
      "date": "2026-04-03",
      "action": "buy",
      "from_ticker": "TQQQ",
      "to_ticker": "SGOV",
      "state": "D",
      "nav": 6638.47,
      "strategy_return_pct": 1.51
    }
  ],
  "deposits": [
    {
      "date": "2026-03-19",
      "amount": 1006.76,
      "note": "추가입금 자동 감지 ($1014.85 - $8.09)"
    },
    {
      "date": "2026-03-20",
      "amount": 397.58,
      "note": "추가입금 자동 감지 ($439.34 - $41.76)"
    },
    {
      "date": "2026-03-21",
      "amount": 834.7,
      "note": "추가입금 자동 감지 ($864.02 - $29.32)"
    },
    {
      "date": "2026-03-24",
      "amount": 1318.69,
      "note": "추가입금 자동 감지 ($1376.46 - $57.77)"
    },
    {
      "date": "2026-03-28",
      "amount": 1320.74,
      "note": "추가입금 자동 감지 ($1329.22 - $8.48)"
    },
    {
      "date": "2026-04-03",
      "amount": 992.41,
      "note": "추가입금 자동 감지 ($1012.82 - $20.41)"
    }
  ],
  "summary": {
    "updated_at": "2026-04-03 06:52 KST",
    "strategy": "4-Regime v5k",
    "current_ticker": "SGOV",
    "current_state": "D",
    "total_invested": 6539.74,
    "current_nav": 6638.47,
    "strategy_return_pct": 1.51,
    "peak_nav": 6638.47,
    "max_drawdown_pct": -99.65,
    "trade_count": 9,
    "days_running": 21,
    "deposit_count": 6
  },
  "indicators": {
    "date": "2026-04-03",
    "vix": 23.899999618530273,
    "vix3m": 24.81999969482422,
    "vix_bb_upper": 30.70636459612561,
    "vix_shock": false,
    "vix_declining": true,
    "term_structure": 0.9629331149232127,
    "qqq": 584.9600219726562,
    "qqq_ma50": 602.5883459472657,
    "qqq_exit_threshold": 590.54,
    "qqq_below_ma50": true,
    "wti_roc_20": 38.32859474580441,
    "wti_95pct": 39.40161855086697,
    "wti_shock": false,
    "state_a": false,
    "state_b": true,
    "state_b_ts_recent": true,
    "state_b_ts_normalized": true,
    "state_c": false,
    "state_c_vix_declining": true,
    "sc_raw_3d": [
      false,
      false,
      false
    ],
    "tqqq_exit_2day": true
  }
}